Metadata-Version: 2.1
Name: dsndd_probability
Version: 0.1
Summary: Gaussian and Binomial distributions
Author: Roushan Kumar
Author-email: kumarroushan.18@gmail.com
